<?xml version="1.0" encoding="UTF-8"?>
<SETTING_DATA VERSION="1.00"><SETDATA TYPE="SETDATA_PATROL" NAME="SETDATA_PATROL" ONOFF="1"><PARAM TYPE="PARAM_PATROL" NAME="ROW"><PARAM TYPE="PARAM_REQ_COORD" NAME="REQ_COORD" X="447" Y="1295"/><PARAM TYPE="PARAM_REQ_ACTION" NAME="REQ_ACTION" FIRST="4096"/><PARAM TYPE="PARAM_BUFF" NAME="COMMAND"><PARAM TYPE="PARAM_ACTION" NAME="DATA_ACTION" ACTIONID="4112"/></PARAM><PARAM TYPE="PARAM_BUFF" NAME="COMMAND"><PARAM TYPE="PARAM_ACTION" NAME="DATA_ACTION" ACTIONID="4112"/></PARAM><PARAM TYPE="PARAM_BUFF" NAME="COMMAND"><PARAM TYPE="PARAM_ACTION" NAME="DATA_ACTION" ACTIONID="4096"/></PARAM></PARAM><PARAM TYPE="PARAM_PATROL" NAME="ROW"><PARAM TYPE="PARAM_REQ_COORD" NAME="REQ_COORD" X="32" Y="1295"/><PARAM TYPE="PARAM_REQ_ACTION" NAME="REQ_ACTION" FIRST="2048"/><PARAM TYPE="PARAM_BUFF" NAME="COMMAND"><PARAM TYPE="PARAM_ACTION" NAME="DATA_ACTION" ACTIONID="4096"/></PARAM></PARAM><PARAM TYPE="PARAM_PATROL" NAME="ROW"><PARAM TYPE="PARAM_REQ_COORD" NAME="REQ_COORD" X="3647" Y="1295"/><PARAM TYPE="PARAM_REQ_ACTION" NAME="REQ_ACTION" FIRST="4096"/><PARAM TYPE="PARAM_BUFF" NAME="COMMAND"><PARAM TYPE="PARAM_ACTION" NAME="DATA_ACTION" ACTIONID="4112"/></PARAM><PARAM TYPE="PARAM_BUFF" NAME="COMMAND"><PARAM TYPE="PARAM_ACTION" NAME="DATA_ACTION" ACTIONID="4112"/></PARAM><PARAM TYPE="PARAM_BUFF" NAME="COMMAND"><PARAM TYPE="PARAM_ACTION" NAME="DATA_ACTION" ACTIONID="4096"/></PARAM></PARAM><PARAM TYPE="PARAM_PATROL" NAME="ROW"><PARAM TYPE="PARAM_REQ_COORD" NAME="REQ_COORD" X="7359" Y="1295"/><PARAM TYPE="PARAM_REQ_ACTION" NAME="REQ_ACTION" FIRST="4096"/><PARAM TYPE="PARAM_BUFF" NAME="COMMAND"><PARAM TYPE="PARAM_ACTION" NAME="DATA_ACTION" ACTIONID="4112"/></PARAM><PARAM TYPE="PARAM_BUFF" NAME="COMMAND"><PARAM TYPE="PARAM_ACTION" NAME="DATA_ACTION" ACTIONID="4112"/></PARAM><PARAM TYPE="PARAM_BUFF" NAME="COMMAND"><PARAM TYPE="PARAM_ACTION" NAME="DATA_ACTION" ACTIONID="2048"/></PARAM></PARAM><PARAM TYPE="PARAM_PATROL" NAME="ROW"><PARAM TYPE="PARAM_REQ_COORD" NAME="REQ_COORD" X="8640" Y="1295"/><PARAM TYPE="PARAM_REQ_ACTION" NAME="REQ_ACTION" FIRST="2048"/><PARAM TYPE="PARAM_BUFF" NAME="COMMAND"><PARAM TYPE="PARAM_ACTION" NAME="DATA_ACTION" ACTIONID="2064"/></PARAM><PARAM TYPE="PARAM_BUFF" NAME="COMMAND"><PARAM TYPE="PARAM_ACTION" NAME="DATA_ACTION" ACTIONID="2048"/></PARAM></PARAM><PARAM TYPE="PARAM_PATROL" NAME="ROW"><PARAM TYPE="PARAM_REQ_COORD" NAME="REQ_COORD" X="7420" Y="1039"/><PARAM TYPE="PARAM_REQ_ACTION" NAME="REQ_ACTION" FIRST="2048"/><PARAM TYPE="PARAM_BUFF" NAME="COMMAND"><PARAM TYPE="PARAM_ACTION" NAME="DATA_ACTION" ACTIONID="4096"/></PARAM></PARAM><PARAM TYPE="PARAM_PATROL" NAME="ROW"><PARAM TYPE="PARAM_REQ_COORD" NAME="REQ_COORD" X="7499" Y="1039"/><PARAM TYPE="PARAM_REQ_ACTION" NAME="REQ_ACTION" FIRST="2048"/><PARAM TYPE="PARAM_BUFF" NAME="COMMAND"><PARAM TYPE="PARAM_ACTION" NAME="DATA_ACTION" ACTIONID="4096"/></PARAM></PARAM><PARAM TYPE="PARAM_PATROL" NAME="ROW"><PARAM TYPE="PARAM_REQ_COORD" NAME="REQ_COORD" X="9410" Y="1295"/><PARAM TYPE="PARAM_REQ_ACTION" NAME="REQ_ACTION" FIRST="4096"/><PARAM TYPE="PARAM_BUFF" NAME="COMMAND"><PARAM TYPE="PARAM_MAPEVENT" NAME="DATA_EVENT"/></PARAM><PARAM TYPE="PARAM_BUFF" NAME="COMMAND"><PARAM TYPE="PARAM_ACTION" NAME="DATA_ACTION" ACTIONID="4096"/></PARAM></PARAM><PARAM TYPE="PARAM_PATROL" NAME="ROW"><PARAM TYPE="PARAM_REQ_COORD" NAME="REQ_COORD" X="4799" Y="783"/><PARAM TYPE="PARAM_REQ_ACTION" NAME="REQ_ACTION" FIRST="4096"/><PARAM TYPE="PARAM_BUFF" NAME="COMMAND"><PARAM TYPE="PARAM_ACTION" NAME="DATA_ACTION" ACTIONID="4112"/></PARAM><PARAM TYPE="PARAM_BUFF" NAME="COMMAND"><PARAM TYPE="PARAM_ACTION" NAME="DATA_ACTION" ACTIONID="4112"/></PARAM><PARAM TYPE="PARAM_BUFF" NAME="COMMAND"><PARAM TYPE="PARAM_ACTION" NAME="DATA_ACTION" ACTIONID="4096"/></PARAM></PARAM></SETDATA><SETDATA TYPE="SETDATA_BASE" NAME="SETDATA_PATROL_AUTO" ONOFF="1"/></SETTING_DATA>
